{
    "Employee's first Name": "Trevor",
    "Employee's initial": "",
    "Employee's last Name": "Duncan",
    "Employee's address": "41435 Hughes Drive, New Teresaberg, KS",
    "Employee's zip code":"99528-9775",
    "Employee's Social security number":"768-05-9800",
    "Employer's identification number":"83-1015714",
    "Employer's name":"White PLC Inc",
    "Employer's address":"21769 Walker Landing, Bakerfurt, NJ",
    "Employer's zip code":"06199-9819",
    "Employer's state":["AL", "IA"],
    "Employer's state ID number":["703-50-377", "882-63-902"],
    "Employer's state wages, tips":["76475.69", "89324.57"],
    "Employer's state income tax":["4802.83", "4795.84"],
    "Employer's local wages, tips":["124601.64","137013.88"],
    "Employer's local income tax":["29884.95","24146.13"],
    "Employer's Locality name":["John Manors", "Gary Loop"],
    "Wages, tips, other compensation":"168250.2",
    "Federal income tax withheld":"53860.77",
    "Social security wages":"159372.62",
    "Social security tax withheld":"12192.01",
    "Medicare wages and tips":"206499.26",
    "Medicare tax withheld":"5988.48",
    "Social security tips":"159372.62",
    "Allocated tips":"206499.26",
    "Advance EIC payment":"",
    "Dependent care benefits":"164",
    "Nonqualified plans":"149",
    "Statutory employee":"",
    "Retirement plan":"",
    "Third-payer sick pay":"",
    "year":"2010"
}
